{
  "w": 480,
  "h": 270,
  "nm": "Synfig Animation 1",
  "ddd": 0,
  "v": "5.3.4",
  "fr": 24.0,
  "assets": [],
  "markers": [],
  "ip": 0.0,
  "op": 121.0,
  "layers": [
    {
      "ddd": 0,
      "ind": 0,
      "ty": 1,
      "nm": "Circle003",
      "sr": 1,
      "ks": {
        "o": { "k": 100, "ix": 1, "a": 0 },
        "r": { "k": 0, "ix": 2, "a": 0 },
        "p": { "k": [240.0, 135.0], "ix": 0, "a": 0 },
        "a": { "k": [240.0, 135.0], "ix": 3, "a": 0 },
        "s": { "k": [100, 100, 100], "ix": 4, "a": 0 },
        "sk": { "k": 0, "ix": 5, "a": 0 },
        "sa": { "k": 0, "ix": 6, "a": 0 }
      },
      "ef": [
        {
          "ty": 21,
          "nm": "Fill",
          "ix": 0,
          "ef": [
            {
              "ty": 10,
              "nm": "Fill Mask",
              "ix": 0,
              "v": { "k": 0, "ix": 0, "a": 0 }
            },
            {
              "ty": 7,
              "nm": "All Masks",
              "ix": 1,
              "v": { "k": 0, "ix": 0, "a": 0 }
            },
            {
              "ty": 2,
              "nm": "Color",
              "ix": 2,
              "v": {
                "ix": 0,
                "a": 1,
                "k": [
                  {
                    "t": 0,
                    "s": [1.0, 1.0, 1.0, 1.0],
                    "e": [1.0, 1.0, 1.0, 1.0],
                    "h": 1
                  },
                  { "t": 1, "h": 1, "s": [1.0, 1.0, 1.0, 1.0] }
                ]
              }
            },
            {
              "ty": 7,
              "nm": "Invert",
              "ix": 3,
              "v": { "k": 0, "ix": 0, "a": 0 }
            },
            {
              "ty": 0,
              "nm": "Horizontal Feather",
              "ix": 4,
              "v": { "k": 0, "ix": 0, "a": 0 }
            },
            {
              "ty": 0,
              "nm": "Vertical Feather",
              "ix": 5,
              "v": { "k": 0, "ix": 0, "a": 0 }
            },
            {
              "ty": 0,
              "nm": "Opacity",
              "ix": 6,
              "v": {
                "ix": 0,
                "a": 1,
                "k": [
                  { "t": 0, "s": [1.0], "e": [1.0], "h": 1 },
                  { "t": 1, "h": 1, "s": [1.0] }
                ]
              }
            }
          ]
        }
      ],
      "ao": 0,
      "sw": 480,
      "sh": 270,
      "sc": "#000000",
      "ip": 0.0,
      "op": 121.0,
      "st": 0,
      "bm": 0,
      "hasMask": true,
      "masksProperties": [
        {
          "inv": false,
          "mode": "a",
          "pt": {
            "ix": 0,
            "a": 1,
            "k": [
              {
                "i": { "x": 0.5, "y": 0.5 },
                "o": { "x": 0.5, "y": 0.5 },
                "t": 0,
                "s": [
                  {
                    "i": [
                      [0, 0],
                      [4.901, 4.897],
                      [6.89, -0.01],
                      [4.897, -4.901],
                      [-0.01, -6.89],
                      [-4.901, -4.897],
                      [-6.89, 0.01],
                      [-4.897, 4.901],
                      [0.01, 6.89]
                    ],
                    "o": [
                      [0.013, -6.909],
                      [-4.906, -4.865],
                      [-6.892, -0.018],
                      [-4.865, 4.906],
                      [-0.018, 6.892],
                      [4.906, 4.865],
                      [6.892, 0.018],
                      [4.865, -4.906],
                      [0, 0]
                    ],
                    "v": [
                      [263.0, 119.0],
                      [255.668, 101.291],
                      [237.974, 94.008],
                      [220.291, 101.332],
                      [213.008, 119.026],
                      [220.332, 136.709],
                      [238.026, 143.992],
                      [255.709, 136.668],
                      [262.992, 118.974]
                    ],
                    "c": true
                  }
                ],
                "e": [
                  {
                    "i": [
                      [0, 0],
                      [5.058, 5.049],
                      [7.157, 0.017],
                      [5.048, -5.061],
                      [0.017, -7.157],
                      [-5.061, -5.048],
                      [-7.157, -0.017],
                      [-5.048, 5.061],
                      [-0.017, 7.157]
                    ],
                    "o": [
                      [0.018, -7.141],
                      [-5.036, -5.063],
                      [-7.148, -0.009],
                      [-5.048, 5.073],
                      [-0.009, 7.148],
                      [5.073, 5.048],
                      [7.148, 0.009],
                      [5.048, -5.073],
                      [0, 0]
                    ],
                    "v": [
                      [263.833, 119.0],
                      [256.274, 100.715],
                      [237.985, 93.094],
                      [219.692, 100.671],
                      [212.094, 119.015],
                      [219.671, 137.308],
                      [238.015, 144.906],
                      [256.308, 137.329],
                      [263.906, 118.985]
                    ],
                    "c": true
                  }
                ]
              },
              {
                "i": { "x": 0.5, "y": 0.5 },
                "o": { "x": 0.5, "y": 0.5 },
                "t": 1,
                "s": [
                  {
                    "i": [
                      [0, 0],
                      [5.058, 5.049],
                      [7.157, 0.017],
                      [5.048, -5.061],
                      [0.017, -7.157],
                      [-5.061, -5.048],
                      [-7.157, -0.017],
                      [-5.048, 5.061],
                      [-0.017, 7.157]
                    ],
                    "o": [
                      [0.018, -7.141],
                      [-5.036, -5.063],
                      [-7.148, -0.009],
                      [-5.048, 5.073],
                      [-0.009, 7.148],
                      [5.073, 5.048],
                      [7.148, 0.009],
                      [5.048, -5.073],
                      [0, 0]
                    ],
                    "v": [
                      [263.833, 119.0],
                      [256.274, 100.715],
                      [237.985, 93.094],
                      [219.692, 100.671],
                      [212.094, 119.015],
                      [219.671, 137.308],
                      [238.015, 144.906],
                      [256.308, 137.329],
                      [263.906, 118.985]
                    ],
                    "c": true
                  }
                ],
                "e": [
                  {
                    "i": [
                      [0, 0],
                      [5.211, 5.202],
                      [7.351, -0.009],
                      [5.202, -5.211],
                      [-0.009, -7.351],
                      [-5.211, -5.202],
                      [-7.351, 0.009],
                      [-5.202, 5.211],
                      [0.009, 7.351]
                    ],
                    "o": [
                      [-0.018, -7.356],
                      [-5.192, -5.204],
                      [-7.363, -0.006],
                      [-5.204, 5.192],
                      [-0.006, 7.363],
                      [5.192, 5.204],
                      [7.363, 0.006],
                      [5.204, -5.192],
                      [0, 0]
                    ],
                    "v": [
                      [264.667, 119.0],
                      [256.824, 100.162],
                      [238.01, 92.369],
                      [219.162, 100.176],
                      [211.369, 118.99],
                      [219.176, 137.838],
                      [237.99, 145.631],
                      [256.838, 137.824],
                      [264.631, 119.01]
                    ],
                    "c": true
                  }
                ]
              },
              {
                "i": { "x": 0.5, "y": 0.5 },
                "o": { "x": 0.5, "y": 0.5 },
                "t": 2,
                "s": [
                  {
                    "i": [
                      [0, 0],
                      [5.211, 5.202],
                      [7.351, -0.009],
                      [5.202, -5.211],
                      [-0.009, -7.351],
                      [-5.211, -5.202],
                      [-7.351, 0.009],
                      [-5.202, 5.211],
                      [0.009, 7.351]
                    ],
                    "o": [
                      [-0.018, -7.356],
                      [-5.192, -5.204],
                      [-7.363, -0.006],
                      [-5.204, 5.192],
                      [-0.006, 7.363],
                      [5.192, 5.204],
                      [7.363, 0.006],
                      [5.204, -5.192],
                      [0, 0]
                    ],
                    "v": [
                      [264.667, 119.0],
                      [256.824, 100.162],
                      [238.01, 92.369],
                      [219.162, 100.176],
                      [211.369, 118.99],
                      [219.176, 137.838],
                      [237.99, 145.631],
                      [256.838, 137.824],
                      [264.631, 119.01]
                    ],
                    "c": true
                  }
                ],
                "e": [
                  {
                    "i": [
                      [0, 0],
                      [5.367, 5.354],
                      [7.6, -0.017],
                      [5.354, -5.367],
                      [-0.017, -7.6],
                      [-5.367, -5.354],
                      [-7.6, 0.017],
                      [-5.354, 5.367],
                      [0.017, 7.6]
                    ],
                    "o": [
                      [-0.013, -7.588],
                      [-5.361, -5.386],
                      [-7.581, -0.009],
                      [-5.386, 5.361],
                      [-0.009, 7.581],
                      [5.361, 5.386],
                      [7.581, 0.009],
                      [5.386, -5.361],
                      [0, 0]
                    ],
                    "v": [
                      [265.5, 119.0],
                      [257.43, 99.587],
                      [237.988, 91.534],
                      [218.587, 99.57],
                      [210.534, 119.012],
                      [218.57, 138.413],
                      [238.012, 146.466],
                      [257.413, 138.43],
                      [265.466, 118.988]
                    ],
                    "c": true
                  }
                ]
              },
              {
                "i": { "x": 0.5, "y": 0.5 },
                "o": { "x": 0.5, "y": 0.5 },
                "t": 3,
                "s": [
                  {
                    "i": [
                      [0, 0],
                      [5.367, 5.354],
                      [7.6, -0.017],
                      [5.354, -5.367],
                      [-0.017, -7.6],
                      [-5.367, -5.354],
                      [-7.6, 0.017],
                      [-5.354, 5.367],
                      [0.017, 7.6]
                    ],
                    "o": [
                      [-0.013, -7.588],
                      [-5.361, -5.386],
                      [-7.581, -0.009],
                      [-5.386, 5.361],
                      [-0.009, 7.581],
                      [5.361, 5.386],
                      [7.581, 0.009],
                      [5.386, -5.361],
                      [0, 0]
                    ],
                    "v": [
                      [265.5, 119.0],
                      [257.43, 99.587],
                      [237.988, 91.534],
                      [218.587, 99.57],
                      [210.534, 119.012],
                      [218.57, 138.413],
                      [238.012, 146.466],
                      [257.413, 138.43],
                      [265.466, 118.988]
                    ],
                    "c": true
                  }
                ],
                "e": [
                  {
                    "i": [
                      [0, 0],
                      [5.538, 5.543],
                      [7.811, -0.011],
                      [5.543, -5.538],
                      [-0.011, -7.811],
                      [-5.538, -5.543],
                      [-7.811, 0.011],
                      [-5.543, 5.538],
                      [0.011, 7.811]
                    ],
                    "o": [
                      [-0.009, -7.82],
                      [-5.516, -5.531],
                      [-7.835, 0.003],
                      [-5.531, 5.516],
                      [0.003, 7.835],
                      [5.516, 5.531],
                      [7.835, -0.003],
                      [5.531, -5.516],
                      [0, 0]
                    ],
                    "v": [
                      [266.333, 119.0],
                      [258.013, 98.956],
                      [238.022, 90.675],
                      [217.956, 98.987],
                      [209.675, 118.978],
                      [217.987, 139.044],
                      [237.978, 147.325],
                      [258.044, 139.013],
                      [266.325, 119.022]
                    ],
                    "c": true
                  }
                ]
              },
              {
                "i": { "x": 0.5, "y": 0.5 },
                "o": { "x": 0.5, "y": 0.5 },
                "t": 4,
                "s": [
                  {
                    "i": [
                      [0, 0],
                      [5.538, 5.543],
                      [7.811, -0.011],
                      [5.543, -5.538],
                      [-0.011, -7.811],
                      [-5.538, -5.543],
                      [-7.811, 0.011],
                      [-5.543, 5.538],
                      [0.011, 7.811]
                    ],
                    "o": [
                      [-0.009, -7.82],
                      [-5.516, -5.531],
                      [-7.835, 0.003],
                      [-5.531, 5.516],
                      [0.003, 7.835],
                      [5.516, 5.531],
                      [7.835, -0.003],
                      [5.531, -5.516],
                      [0, 0]
                    ],
                    "v": [
                      [266.333, 119.0],
                      [258.013, 98.956],
                      [238.022, 90.675],
                      [217.956, 98.987],
                      [209.675, 118.978],
                      [217.987, 139.044],
                      [237.978, 147.325],
                      [258.044, 139.013],
                      [266.325, 119.022]
                    ],
                    "c": true
                  }
                ],
                "e": [
                  {
                    "i": [
                      [0, 0],
                      [5.694, 5.694],
                      [8.06, -0.02],
                      [5.694, -5.694],
                      [-0.02, -8.06],
                      [-5.694, -5.694],
                      [-8.06, 0.02],
                      [-5.694, 5.694],
                      [0.02, 8.06]
                    ],
                    "o": [
                      [-0.004, -8.052],
                      [-5.685, -5.713],
                      [-8.053, 0.0],
                      [-5.713, 5.685],
                      [0.0, 8.053],
                      [5.685, 5.713],
                      [8.053, -0.0],
                      [5.713, -5.685],
                      [0, 0]
                    ],
                    "v": [
                      [267.167, 119.0],
                      [258.619, 98.38],
                      [238.001, 89.84],
                      [217.38, 98.381],
                      [208.84, 118.999],
                      [217.381, 139.62],
                      [237.999, 148.16],
                      [258.62, 139.619],
                      [267.16, 119.001]
                    ],
                    "c": true
                  }
                ]
              },
              {
                "i": { "x": 0.5, "y": 0.5 },
                "o": { "x": 0.5, "y": 0.5 },
                "t": 5,
                "s": [
                  {
                    "i": [
                      [0, 0],
                      [5.694, 5.694],
                      [8.06, -0.02],
                      [5.694, -5.694],
                      [-0.02, -8.06],
                      [-5.694, -5.694],
                      [-8.06, 0.02],
                      [-5.694, 5.694],
                      [0.02, 8.06]
                    ],
                    "o": [
                      [-0.004, -8.052],
                      [-5.685, -5.713],
                      [-8.053, 0.0],
                      [-5.713, 5.685],
                      [0.0, 8.053],
                      [5.685, 5.713],
                      [8.053, -0.0],
                      [5.713, -5.685],
                      [0, 0]
                    ],
                    "v": [
                      [267.167, 119.0],
                      [258.619, 98.38],
                      [238.001, 89.84],
                      [217.38, 98.381],
                      [208.84, 118.999],
                      [217.381, 139.62],
                      [237.999, 148.16],
                      [258.62, 139.619],
                      [267.16, 119.001]
                    ],
                    "c": true
                  }
                ],
                "e": [
                  {
                    "i": [
                      [0, 0],
                      [5.85, 5.846],
                      [8.288, 0.027],
                      [5.849, -5.852],
                      [0.03, -8.289],
                      [-5.849, -5.85],
                      [-8.271, 0.006],
                      [-5.849, 5.844],
                      [-0.011, 8.231]
                    ],
                    "o": [
                      [-0.0, -8.284],
                      [-5.838, -5.855],
                      [-8.268, -0.004],
                      [-5.852, 5.837],
                      [-0.001, 8.266],
                      [5.84, 5.851],
                      [8.268, -0.003],
                      [5.812, -5.828],
                      [0, 0]
                    ],
                    "v": [
                      [268.0, 119.0],
                      [259.224, 97.804],
                      [238.035, 88.982],
                      [216.86, 97.753],
                      [208.037, 118.942],
                      [216.808, 140.117],
                      [237.974, 148.885],
                      [259.15, 140.114],
                      [267.885, 119.026]
                    ],
                    "c": true
                  }
                ]
              },
              {
                "i": { "x": 0.5, "y": 0.5 },
                "o": { "x": 0.5, "y": 0.5 },
                "t": 6,
                "s": [
                  {
                    "i": [
                      [0, 0],
                      [5.85, 5.846],
                      [8.288, 0.027],
                      [5.849, -5.852],
                      [0.03, -8.289],
                      [-5.849, -5.85],
                      [-8.271, 0.006],
                      [-5.849, 5.844],
                      [-0.011, 8.231]
                    ],
                    "o": [
                      [-0.0, -8.284],
                      [-5.838, -5.855],
                      [-8.268, -0.004],
                      [-5.852, 5.837],
                      [-0.001, 8.266],
                      [5.84, 5.851],
                      [8.268, -0.003],
                      [5.812, -5.828],
                      [0, 0]
                    ],
                    "v": [
                      [268.0, 119.0],
                      [259.224, 97.804],
                      [238.035, 88.982],
                      [216.86, 97.753],
                      [208.037, 118.942],
                      [216.808, 140.117],
                      [237.974, 148.885],
                      [259.15, 140.114],
                      [267.885, 119.026]
                    ],
                    "c": true
                  }
                ],
                "e": [
                  {
                    "i": [
                      [0, 0],
                      [6.022, 6.035],
                      [8.517, -0.02],
                      [6.017, -6.058],
                      [-0.019, -8.514],
                      [-6.038, -5.978],
                      [-8.495, 0.055],
                      [-5.979, 6.035],
                      [0.054, 8.492]
                    ],
                    "o": [
                      [0.004, -8.516],
                      [-6.049, -6.023],
                      [-8.528, 0.011],
                      [-5.985, 6.037],
                      [0.052, 8.515],
                      [6.04, 5.984],
                      [8.477, -0.04],
                      [5.982, -6.043],
                      [0, 0]
                    ],
                    "v": [
                      [268.833, 119.0],
                      [259.807, 97.173],
                      [237.958, 88.169],
                      [216.141, 97.271],
                      [207.192, 119.097],
                      [216.327, 140.836],
                      [238.13, 149.73],
                      [259.813, 140.618],
                      [268.707, 118.815]
                    ],
                    "c": true
                  }
                ]
              },
              {
                "i": { "x": 0.5, "y": 0.5 },
                "o": { "x": 0.5, "y": 0.5 },
                "t": 7,
                "s": [
                  {
                    "i": [
                      [0, 0],
                      [6.022, 6.035],
                      [8.517, -0.02],
                      [6.017, -6.058],
                      [-0.019, -8.514],
                      [-6.038, -5.978],
                      [-8.495, 0.055],
                      [-5.979, 6.035],
                      [0.054, 8.492]
                    ],
                    "o": [
                      [0.004, -8.516],
                      [-6.049, -6.023],
                      [-8.528, 0.011],
                      [-5.985, 6.037],
                      [0.052, 8.515],
                      [6.04, 5.984],
                      [8.477, -0.04],
                      [5.982, -6.043],
                      [0, 0]
                    ],
                    "v": [
                      [268.833, 119.0],
                      [259.807, 97.173],
                      [237.958, 88.169],
                      [216.141, 97.271],
                      [207.192, 119.097],
                      [216.327, 140.836],
                      [238.13, 149.73],
                      [259.813, 140.618],
                      [268.707, 118.815]
                    ],
                    "c": true
                  }
                ],
                "e": [
                  {
                    "i": [
                      [0, 0],
                      [6.178, 6.187],
                      [8.748, 0.025],
                      [6.225, -6.198],
                      [0.007, -8.784],
                      [-6.217, -6.167],
                      [-8.765, 0.029],
                      [-6.168, 6.214],
                      [0.013, 8.725]
                    ],
                    "o": [
                      [0.009, -8.748],
                      [-6.162, -6.182],
                      [-8.757, -0.035],
                      [-6.206, 6.216],
                      [0.02, 8.784],
                      [6.203, 6.168],
                      [8.746, -0.007],
                      [6.167, -6.206],
                      [0, 0]
                    ],
                    "v": [
                      [269.667, 119.0],
                      [260.413, 96.598],
                      [238.048, 87.288],
                      [215.575, 96.531],
                      [206.255, 119.031],
                      [215.61, 141.458],
                      [238.063, 150.666],
                      [260.435, 141.335],
                      [269.666, 118.937]
                    ],
                    "c": true
                  }
                ]
              },
              {
                "i": { "x": 0.5, "y": 0.5 },
                "o": { "x": 0.5, "y": 0.5 },
                "t": 8,
                "s": [
                  {
                    "i": [
                      [0, 0],
                      [6.178, 6.187],
                      [8.748, 0.025],
                      [6.225, -6.198],
                      [0.007, -8.784],
                      [-6.217, -6.167],
                      [-8.765, 0.029],
                      [-6.168, 6.214],
                      [0.013, 8.725]
                    ],
                    "o": [
                      [0.009, -8.748],
                      [-6.162, -6.182],
                      [-8.757, -0.035],
                      [-6.206, 6.216],
                      [0.02, 8.784],
                      [6.203, 6.168],
                      [8.746, -0.007],
                      [6.167, -6.206],
                      [0, 0]
                    ],
                    "v": [
                      [269.667, 119.0],
                      [260.413, 96.598],
                      [238.048, 87.288],
                      [215.575, 96.531],
                      [206.255, 119.031],
                      [215.61, 141.458],
                      [238.063, 150.666],
                      [260.435, 141.335],
                      [269.666, 118.937]
                    ],
                    "c": true
                  }
                ],
                "e": [
                  {
                    "i": [
                      [0, 0],
                      [6.334, 6.339],
                      [8.997, 0.016],
                      [6.339, -6.334],
                      [0.016, -8.997],
                      [-6.334, -6.339],
                      [-8.997, -0.016],
                      [-6.339, 6.334],
                      [-0.016, 8.997]
                    ],
                    "o": [
                      [0.013, -8.98],
                      [-6.332, -6.364],
                      [-8.998, 0.018],
                      [-6.364, 6.332],
                      [0.018, 8.998],
                      [6.332, 6.364],
                      [8.998, -0.018],
                      [6.364, -6.332],
                      [0, 0]
                    ],
                    "v": [
                      [270.5, 119.0],
                      [261.019, 96.022],
                      [238.027, 86.452],
                      [215.022, 95.981],
                      [205.452, 118.973],
                      [214.981, 141.978],
                      [237.973, 151.548],
                      [260.978, 142.019],
                      [270.548, 119.027]
                    ],
                    "c": true
                  }
                ]
              },
              {
                "i": { "x": 0.5, "y": 0.5 },
                "o": { "x": 0.5, "y": 0.5 },
                "t": 9,
                "s": [
                  {
                    "i": [
                      [0, 0],
                      [6.334, 6.339],
                      [8.997, 0.016],
                      [6.339, -6.334],
                      [0.016, -8.997],
                      [-6.334, -6.339],
                      [-8.997, -0.016],
                      [-6.339, 6.334],
                      [-0.016, 8.997]
                    ],
                    "o": [
                      [0.013, -8.98],
                      [-6.332, -6.364],
                      [-8.998, 0.018],
                      [-6.364, 6.332],
                      [0.018, 8.998],
                      [6.332, 6.364],
                      [8.998, -0.018],
                      [6.364, -6.332],
                      [0, 0]
                    ],
                    "v": [
                      [270.5, 119.0],
                      [261.019, 96.022],
                      [238.027, 86.452],
                      [215.022, 95.981],
                      [205.452, 118.973],
                      [214.981, 141.978],
                      [237.973, 151.548],
                      [260.978, 142.019],
                      [270.548, 119.027]
                    ],
                    "c": true
                  }
                ],
                "e": [
                  {
                    "i": [
                      [0, 0],
                      [6.505, 6.527],
                      [9.19, -0.013],
                      [6.492, -6.487],
                      [0.027, -9.206],
                      [-6.487, -6.492],
                      [-9.206, -0.027],
                      [-6.492, 6.487],
                      [-0.027, 9.206]
                    ],
                    "o": [
                      [0.018, -9.212],
                      [-6.526, -6.492],
                      [-9.214, 0.018],
                      [-6.504, 6.488],
                      [0.018, 9.214],
                      [6.488, 6.504],
                      [9.214, -0.018],
                      [6.504, -6.488],
                      [0, 0]
                    ],
                    "v": [
                      [271.333, 119.0],
                      [261.602, 95.391],
                      [238.028, 85.672],
                      [214.469, 95.431],
                      [204.672, 118.972],
                      [214.431, 142.531],
                      [237.972, 152.328],
                      [261.531, 142.569],
                      [271.328, 119.028]
                    ],
                    "c": true
                  }
                ]
              },
              {
                "i": { "x": 0.5, "y": 0.5 },
                "o": { "x": 0.5, "y": 0.5 },
                "t": 10,
                "s": [
                  {
                    "i": [
                      [0, 0],
                      [6.505, 6.527],
                      [9.19, -0.013],
                      [6.492, -6.487],
                      [0.027, -9.206],
                      [-6.487, -6.492],
                      [-9.206, -0.027],
                      [-6.492, 6.487],
                      [-0.027, 9.206]
                    ],
                    "o": [
                      [0.018, -9.212],
                      [-6.526, -6.492],
                      [-9.214, 0.018],
                      [-6.504, 6.488],
                      [0.018, 9.214],
                      [6.488, 6.504],
                      [9.214, -0.018],
                      [6.504, -6.488],
                      [0, 0]
                    ],
                    "v": [
                      [271.333, 119.0],
                      [261.602, 95.391],
                      [238.028, 85.672],
                      [214.469, 95.431],
                      [204.672, 118.972],
                      [214.431, 142.531],
                      [237.972, 152.328],
                      [261.531, 142.569],
                      [271.328, 119.028]
                    ],
                    "c": true
                  }
                ],
                "e": [
                  {
                    "i": [
                      [0, 0],
                      [6.659, 6.68],
                      [9.454, 0.015],
                      [6.679, -6.662],
                      [0.015, -9.454],
                      [-6.662, -6.679],
                      [-9.454, -0.015],
                      [-6.679, 6.662],
                      [-0.015, 9.454]
                    ],
                    "o": [
                      [-0.018, -9.428],
                      [-6.659, -6.689],
                      [-9.433, 0.012],
                      [-6.674, 6.696],
                      [0.012, 9.433],
                      [6.696, 6.674],
                      [9.433, -0.012],
                      [6.674, -6.696],
                      [0, 0]
                    ],
                    "v": [
                      [272.167, 119.0],
                      [262.152, 94.838],
                      [237.984, 84.781],
                      [213.815, 94.792],
                      [203.781, 119.016],
                      [213.792, 143.185],
                      [238.016, 153.219],
                      [262.185, 143.208],
                      [272.219, 118.984]
                    ],
                    "c": true
                  }
                ]
              },
              {
                "i": { "x": 0.5, "y": 0.5 },
                "o": { "x": 0.5, "y": 0.5 },
                "t": 11,
                "s": [
                  {
                    "i": [
                      [0, 0],
                      [6.659, 6.68],
                      [9.454, 0.015],
                      [6.679, -6.662],
                      [0.015, -9.454],
                      [-6.662, -6.679],
                      [-9.454, -0.015],
                      [-6.679, 6.662],
                      [-0.015, 9.454]
                    ],
                    "o": [
                      [-0.018, -9.428],
                      [-6.659, -6.689],
                      [-9.433, 0.012],
                      [-6.674, 6.696],
                      [0.012, 9.433],
                      [6.696, 6.674],
                      [9.433, -0.012],
                      [6.674, -6.696],
                      [0, 0]
                    ],
                    "v": [
                      [272.167, 119.0],
                      [262.152, 94.838],
                      [237.984, 84.781],
                      [213.815, 94.792],
                      [203.781, 119.016],
                      [213.792, 143.185],
                      [238.016, 153.219],
                      [262.185, 143.208],
                      [272.219, 118.984]
                    ],
                    "c": true
                  }
                ],
                "e": [
                  {
                    "i": [
                      [0, 0],
                      [6.815, 6.832],
                      [9.666, 0.025],
                      [6.871, -6.834],
                      [0.005, -9.705],
                      [-6.873, -6.851],
                      [-9.701, -0.003],
                      [-6.848, 6.872],
                      [0.037, 9.684]
                    ],
                    "o": [
                      [-0.013, -9.659],
                      [-6.812, -6.831],
                      [-9.663, -0.029],
                      [-6.872, 6.825],
                      [-0.015, 9.705],
                      [6.866, 6.859],
                      [9.692, -0.023],
                      [6.862, -6.868],
                      [0, 0]
                    ],
                    "v": [
                      [273.0, 119.0],
                      [262.758, 94.263],
                      [238.041, 83.978],
                      [213.24, 94.187],
                      [202.923, 118.982],
                      [213.21, 143.816],
                      [238.06, 154.109],
                      [262.871, 143.767],
                      [273.109, 118.94]
                    ],
                    "c": true
                  }
                ]
              },
              {
                "i": { "x": 0.5, "y": 0.5 },
                "o": { "x": 0.5, "y": 0.5 },
                "t": 12,
                "s": [
                  {
                    "i": [
                      [0, 0],
                      [6.815, 6.832],
                      [9.666, 0.025],
                      [6.871, -6.834],
                      [0.005, -9.705],
                      [-6.873, -6.851],
                      [-9.701, -0.003],
                      [-6.848, 6.872],
                      [0.037, 9.684]
                    ],
                    "o": [
                      [-0.013, -9.659],
                      [-6.812, -6.831],
                      [-9.663, -0.029],
                      [-6.872, 6.825],
                      [-0.015, 9.705],
                      [6.866, 6.859],
                      [9.692, -0.023],
                      [6.862, -6.868],
                      [0, 0]
                    ],
                    "v": [
                      [273.0, 119.0],
                      [262.758, 94.263],
                      [238.041, 83.978],
                      [213.24, 94.187],
                      [202.923, 118.982],
                      [213.21, 143.816],
                      [238.06, 154.109],
                      [262.871, 143.767],
                      [273.109, 118.94]
                    ],
                    "c": true
                  }
                ],
                "e": [
                  {
                    "i": [
                      [0, 0],
                      [6.971, 6.984],
                      [9.915, 0.016],
                      [7.004, -7.026],
                      [-0.023, -9.895],
                      [-7.007, -6.966],
                      [-9.894, 0.018],
                      [-6.967, 7.003],
                      [0.002, 9.854]
                    ],
                    "o": [
                      [-0.009, -9.891],
                      [-6.981, -7.013],
                      [-9.921, -0.015],
                      [-7.0, 7.022],
                      [0.026, 9.908],
                      [7.009, 6.958],
                      [9.869, -0.014],
                      [6.957, -7.012],
                      [0, 0]
                    ],
                    "v": [
                      [273.833, 119.0],
                      [263.364, 93.687],
                      [238.02, 83.143],
                      [212.631, 93.659],
                      [202.166, 119.036],
                      [212.715, 144.346],
                      [238.068, 154.756],
                      [263.323, 144.23],
                      [273.756, 118.932]
                    ],
                    "c": true
                  }
                ]
              },
              {
                "i": { "x": 0.5, "y": 0.5 },
                "o": { "x": 0.5, "y": 0.5 },
                "t": 13,
                "s": [
                  {
                    "i": [
                      [0, 0],
                      [6.971, 6.984],
                      [9.915, 0.016],
                      [7.004, -7.026],
                      [-0.023, -9.895],
                      [-7.007, -6.966],
                      [-9.894, 0.018],
                      [-6.967, 7.003],
                      [0.002, 9.854]
                    ],
                    "o": [
                      [-0.009, -9.891],
                      [-6.981, -7.013],
                      [-9.921, -0.015],
                      [-7.0, 7.022],
                      [0.026, 9.908],
                      [7.009, 6.958],
                      [9.869, -0.014],
                      [6.957, -7.012],
                      [0, 0]
                    ],
                    "v": [
                      [273.833, 119.0],
                      [263.364, 93.687],
                      [238.02, 83.143],
                      [212.631, 93.659],
                      [202.166, 119.036],
                      [212.715, 144.346],
                      [238.068, 154.756],
                      [263.323, 144.23],
                      [273.756, 118.932]
                    ],
                    "c": true
                  }
                ],
                "e": [
                  {
                    "i": [
                      [0, 0],
                      [7.179, 7.157],
                      [10.108, -0.013],
                      [7.157, -7.179],
                      [-0.013, -10.108],
                      [-7.179, -7.157],
                      [-10.108, 0.013],
                      [-7.157, 7.179],
                      [0.013, 10.108]
                    ],
                    "o": [
                      [-0.004, -10.123],
                      [-7.138, -7.157],
                      [-10.138, -0.015],
                      [-7.157, 7.138],
                      [-0.015, 10.138],
                      [7.138, 7.157],
                      [10.138, 0.015],
                      [7.157, -7.138],
                      [0, 0]
                    ],
                    "v": [
                      [274.667, 119.0],
                      [263.891, 93.079],
                      [238.021, 82.363],
                      [212.079, 93.109],
                      [201.363, 118.979],
                      [212.109, 144.921],
                      [237.979, 155.637],
                      [263.921, 144.891],
                      [274.637, 119.021]
                    ],
                    "c": true
                  }
                ]
              },
              {
                "i": { "x": 0.5, "y": 0.5 },
                "o": { "x": 0.5, "y": 0.5 },
                "t": 14,
                "s": [
                  {
                    "i": [
                      [0, 0],
                      [7.179, 7.157],
                      [10.108, -0.013],
                      [7.157, -7.179],
                      [-0.013, -10.108],
                      [-7.179, -7.157],
                      [-10.108, 0.013],
                      [-7.157, 7.179],
                      [0.013, 10.108]
                    ],
                    "o": [
                      [-0.004, -10.123],
                      [-7.138, -7.157],
                      [-10.138, -0.015],
                      [-7.157, 7.138],
                      [-0.015, 10.138],
                      [7.138, 7.157],
                      [10.138, 0.015],
                      [7.157, -7.138],
                      [0, 0]
                    ],
                    "v": [
                      [274.667, 119.0],
                      [263.891, 93.079],
                      [238.021, 82.363],
                      [212.079, 93.109],
                      [201.363, 118.979],
                      [212.109, 144.921],
                      [237.979, 155.637],
                      [263.921, 144.891],
                      [274.637, 119.021]
                    ],
                    "c": true
                  }
                ],
                "e": [
                  {
                    "i": [
                      [0, 0],
                      [7.335, 7.309],
                      [10.372, 0.015],
                      [7.309, -7.335],
                      [0.015, -10.372],
                      [-7.335, -7.309],
                      [-10.372, -0.015],
                      [-7.309, 7.335],
                      [-0.015, 10.372]
                    ],
                    "o": [
                      [-0.0, -10.355],
                      [-7.308, -7.339],
                      [-10.34, 0.019],
                      [-7.339, 7.308],
                      [0.019, 10.34],
                      [7.308, 7.339],
                      [10.34, -0.019],
                      [7.339, -7.308],
                      [0, 0]
                    ],
                    "v": [
                      [275.5, 119.0],
                      [264.497, 92.503],
                      [237.977, 81.472],
                      [211.503, 92.503],
                      [200.472, 119.023],
                      [211.503, 145.497],
                      [238.023, 156.528],
                      [264.497, 145.497],
                      [275.528, 118.977]
                    ],
                    "c": true
                  }
                ]
              },
              {
                "i": { "x": 0.5, "y": 0.5 },
                "o": { "x": 0.5, "y": 0.5 },
                "t": 15,
                "s": [
                  {
                    "i": [
                      [0, 0],
                      [7.335, 7.309],
                      [10.372, 0.015],
                      [7.309, -7.335],
                      [0.015, -10.372],
                      [-7.335, -7.309],
                      [-10.372, -0.015],
                      [-7.309, 7.335],
                      [-0.015, 10.372]
                    ],
                    "o": [
                      [-0.0, -10.355],
                      [-7.308, -7.339],
                      [-10.34, 0.019],
                      [-7.339, 7.308],
                      [0.019, 10.34],
                      [7.308, 7.339],
                      [10.34, -0.019],
                      [7.339, -7.308],
                      [0, 0]
                    ],
                    "v": [
                      [275.5, 119.0],
                      [264.497, 92.503],
                      [237.977, 81.472],
                      [211.503, 92.503],
                      [200.472, 119.023],
                      [211.503, 145.497],
                      [238.023, 156.528],
                      [264.497, 145.497],
                      [275.528, 118.977]
                    ],
                    "c": true
                  }
                ],
                "e": [
                  {
                    "i": [
                      [0, 0],
                      [7.507, 7.498],
                      [10.565, -0.014],
                      [7.462, -7.488],
                      [-0.011, -10.567],
                      [-7.488, -7.462],
                      [-10.567, 0.011],
                      [-7.462, 7.488],
                      [0.011, 10.567]
                    ],
                    "o": [
                      [0.004, -10.587],
                      [-7.502, -7.467],
                      [-10.556, 0.019],
                      [-7.479, 7.464],
                      [-0.018, 10.572],
                      [7.464, 7.479],
                      [10.572, 0.018],
                      [7.479, -7.464],
                      [0, 0]
                    ],
                    "v": [
                      [276.333, 119.0],
                      [265.08, 91.872],
                      [237.979, 80.692],
                      [210.95, 91.953],
                      [199.748, 118.998],
                      [210.953, 146.05],
                      [237.998, 157.252],
                      [265.05, 146.047],
                      [276.252, 119.002]
                    ],
                    "c": true
                  }
                ]
              },
              {
                "i": { "x": 0.5, "y": 0.5 },
                "o": { "x": 0.5, "y": 0.5 },
                "t": 16,
                "s": [
                  {
                    "i": [
                      [0, 0],
                      [7.507, 7.498],
                      [10.565, -0.014],
                      [7.462, -7.488],
                      [-0.011, -10.567],
                      [-7.488, -7.462],
                      [-10.567, 0.011],
                      [-7.462, 7.488],
                      [0.011, 10.567]
                    ],
                    "o": [
                      [0.004, -10.587],
                      [-7.502, -7.467],
                      [-10.556, 0.019],
                      [-7.479, 7.464],
                      [-0.018, 10.572],
                      [7.464, 7.479],
                      [10.572, 0.018],
                      [7.479, -7.464],
                      [0, 0]
                    ],
                    "v": [
                      [276.333, 119.0],
                      [265.08, 91.872],
                      [237.979, 80.692],
                      [210.95, 91.953],
                      [199.748, 118.998],
                      [210.953, 146.05],
                      [237.998, 157.252],
                      [265.05, 146.047],
                      [276.252, 119.002]
                    ],
                    "c": true
                  }
                ],
                "e": [
                  {
                    "i": [
                      [0, 0],
                      [7.663, 7.65],
                      [10.814, -0.023],
                      [7.611, -7.643],
                      [-0.02, -10.815],
                      [-7.641, -7.615],
                      [-10.776, -0.0],
                      [-7.615, 7.641],
                      [-0.0, 10.776]
                    ],
                    "o": [
                      [0.009, -10.819],
                      [-7.672, -7.649],
                      [-10.814, 0.032],
                      [-7.624, 7.618],
                      [0.019, 10.773],
                      [7.62, 7.62],
                      [10.788, 0.018],
                      [7.62, -7.62],
                      [0, 0]
                    ],
                    "v": [
                      [277.167, 119.0],
                      [265.686, 91.296],
                      [237.957, 79.857],
                      [210.319, 91.37],
                      [198.912, 119.02],
                      [210.402, 146.602],
                      [237.997, 158.032],
                      [265.602, 146.598],
                      [277.032, 119.003]
                    ],
                    "c": true
                  }
                ]
              },
              {
                "i": { "x": 0.5, "y": 0.5 },
                "o": { "x": 0.5, "y": 0.5 },
                "t": 17,
                "s": [
                  {
                    "i": [
                      [0, 0],
                      [7.663, 7.65],
                      [10.814, -0.023],
                      [7.611, -7.643],
                      [-0.02, -10.815],
                      [-7.641, -7.615],
                      [-10.776, -0.0],
                      [-7.615, 7.641],
                      [-0.0, 10.776]
                    ],
                    "o": [
                      [0.009, -10.819],
                      [-7.672, -7.649],
                      [-10.814, 0.032],
                      [-7.624, 7.618],
                      [0.019, 10.773],
                      [7.62, 7.62],
                      [10.788, 0.018],
                      [7.62, -7.62],
                      [0, 0]
                    ],
                    "v": [
                      [277.167, 119.0],
                      [265.686, 91.296],
                      [237.957, 79.857],
                      [210.319, 91.37],
                      [198.912, 119.02],
                      [210.402, 146.602],
                      [237.997, 158.032],
                      [265.602, 146.598],
                      [277.032, 119.003]
                    ],
                    "c": true
                  }
                ],
                "e": [
                  {
                    "i": [
                      [0, 0],
                      [7.819, 7.802],
                      [11.045, 0.023],
                      [7.82, -7.783],
                      [0.021, -11.048],
                      [-7.785, -7.823],
                      [-11.049, -0.025],
                      [-7.823, 7.785],
                      [-0.025, 11.049]
                    ],
                    "o": [
                      [0.013, -11.051],
                      [-7.785, -7.807],
                      [-11.042, -0.013],
                      [-7.846, 7.797],
                      [-0.015, 11.039],
                      [7.796, 7.843],
                      [11.055, 0.052],
                      [7.843, -7.796],
                      [0, 0]
                    ],
                    "v": [
                      [278.0, 119.0],
                      [266.292, 90.721],
                      [238.047, 78.975],
                      [209.753, 90.63],
                      [197.952, 118.898],
                      [209.607, 147.191],
                      [237.875, 158.992],
                      [266.191, 147.393],
                      [277.992, 119.125]
                    ],
                    "c": true
                  }
                ]
              },
              {
                "i": { "x": 0.5, "y": 0.5 },
                "o": { "x": 0.5, "y": 0.5 },
                "t": 18,
                "s": [
                  {
                    "i": [
                      [0, 0],
                      [7.819, 7.802],
                      [11.045, 0.023],
                      [7.82, -7.783],
                      [0.021, -11.048],
                      [-7.785, -7.823],
                      [-11.049, -0.025],
                      [-7.823, 7.785],
                      [-0.025, 11.049]
                    ],
                    "o": [
                      [0.013, -11.051],
                      [-7.785, -7.807],
                      [-11.042, -0.013],
                      [-7.846, 7.797],
                      [-0.015, 11.039],
                      [7.796, 7.843],
                      [11.055, 0.052],
                      [7.843, -7.796],
                      [0, 0]
                    ],
                    "v": [
                      [278.0, 119.0],
                      [266.292, 90.721],
                      [238.047, 78.975],
                      [209.753, 90.63],
                      [197.952, 118.898],
                      [209.607, 147.191],
                      [237.875, 158.992],
                      [266.191, 147.393],
                      [277.992, 119.125]
                    ],
                    "c": true
                  }
                ],
                "e": [
                  {
                    "i": [
                      [0, 0],
                      [7.99, 7.99],
                      [11.274, -0.025],
                      [7.99, -7.99],
                      [-0.025, -11.274],
                      [-7.99, -7.99],
                      [-11.274, 0.025],
                      [-7.99, 7.99],
                      [0.025, 11.274]
                    ],
                    "o": [
                      [0.018, -11.283],
                      [-7.996, -7.976],
                      [-11.263, -0.015],
                      [-7.976, 7.996],
                      [-0.015, 11.263],
                      [7.996, 7.976],
                      [11.263, 0.015],
                      [7.976, -7.996],
                      [0, 0]
                    ],
                    "v": [
                      [278.833, 119.0],
                      [266.874, 90.09],
                      [237.97, 78.163],
                      [209.09, 90.126],
                      [197.163, 119.03],
                      [209.126, 147.91],
                      [238.03, 159.837],
                      [266.91, 147.874],
                      [278.837, 118.97]
                    ],
                    "c": true
                  }
                ]
              },
              {
                "i": { "x": 0.5, "y": 0.5 },
                "o": { "x": 0.5, "y": 0.5 },
                "t": 19,
                "s": [
                  {
                    "i": [
                      [0, 0],
                      [7.99, 7.99],
                      [11.274, -0.025],
                      [7.99, -7.99],
                      [-0.025, -11.274],
                      [-7.99, -7.99],
                      [-11.274, 0.025],
                      [-7.99, 7.99],
                      [0.025, 11.274]
                    ],
                    "o": [
                      [0.018, -11.283],
                      [-7.996, -7.976],
                      [-11.263, -0.015],
                      [-7.976, 7.996],
                      [-0.015, 11.263],
                      [7.996, 7.976],
                      [11.263, 0.015],
                      [7.976, -7.996],
                      [0, 0]
                    ],
                    "v": [
                      [278.833, 119.0],
                      [266.874, 90.09],
                      [237.97, 78.163],
                      [209.09, 90.126],
                      [197.163, 119.03],
                      [209.126, 147.91],
                      [238.03, 159.837],
                      [266.91, 147.874],
                      [278.837, 118.97]
                    ],
                    "c": true
                  }
                ],
                "e": [
                  {
                    "i": [
                      [0, 0],
                      [8.143, 8.144],
                      [11.484, -0.014],
                      [8.144, -8.143],
                      [-0.014, -11.484],
                      [-8.143, -8.144],
                      [-11.484, 0.014],
                      [-8.144, 8.143],
                      [0.014, 11.484]
                    ],
                    "o": [
                      [-0.018, -11.499],
                      [-8.152, -8.117],
                      [-11.48, -0.015],
                      [-8.117, 8.152],
                      [-0.015, 11.48],
                      [8.152, 8.117],
                      [11.48, 0.015],
                      [8.117, -8.152],
                      [0, 0]
                    ],
                    "v": [
                      [279.667, 119.0],
                      [267.425, 89.537],
                      [237.972, 77.383],
                      [208.537, 89.575],
                      [196.383, 119.028],
                      [208.575, 148.463],
                      [238.028, 160.617],
                      [267.463, 148.425],
                      [279.617, 118.972]
                    ],
                    "c": true
                  }
                ]
              },
              {
                "i": { "x": 0.5, "y": 0.5 },
                "o": { "x": 0.5, "y": 0.5 },
                "t": 20,
                "s": [
                  {
                    "i": [
                      [0, 0],
                      [8.143, 8.144],
                      [11.484, -0.014],
                      [8.144, -8.143],
                      [-0.014, -11.484],
                      [-8.143, -8.144],
                      [-11.484, 0.014],
                      [-8.144, 8.143],
                      [0.014, 11.484]
                    ],
                    "o": [
                      [-0.018, -11.499],
                      [-8.152, -8.117],
                      [-11.48, -0.015],
                      [-8.117, 8.152],
                      [-0.015, 11.48],
                      [8.152, 8.117],
                      [11.48, 0.015],
                      [8.117, -8.152],
                      [0, 0]
                    ],
                    "v": [
                      [279.667, 119.0],
                      [267.425, 89.537],
                      [237.972, 77.383],
                      [208.537, 89.575],
                      [196.383, 119.028],
                      [208.575, 148.463],
                      [238.028, 160.617],
                      [267.463, 148.425],
                      [279.617, 118.972]
                    ],
                    "c": true
                  }
                ],
                "e": [
                  {
                    "i": [
                      [0, 0],
                      [8.3, 8.295],
                      [11.751, 0.013],
                      [8.294, -8.303],
                      [0.013, -11.751],
                      [-8.303, -8.294],
                      [-11.751, -0.013],
                      [-8.294, 8.303],
                      [-0.013, 11.751]
                    ],
                    "o": [
                      [-0.013, -11.731],
                      [-8.281, -8.315],
                      [-11.736, -0.006],
                      [-8.3, 8.318],
                      [-0.006, 11.736],
                      [8.318, 8.3],
                      [11.736, 0.006],
                      [8.3, -8.318],
                      [0, 0]
                    ],
                    "v": [
                      [280.5, 119.0],
                      [268.031, 88.961],
                      [237.983, 76.469],
                      [207.938, 88.914],
                      [195.469, 119.017],
                      [207.914, 149.062],
                      [238.017, 161.531],
                      [268.062, 149.086],
                      [280.531, 118.983]
                    ],
                    "c": true
                  }
                ]
              },
              {
                "i": { "x": 0.5, "y": 0.5 },
                "o": { "x": 0.5, "y": 0.5 },
                "t": 21,
                "s": [
                  {
                    "i": [
                      [0, 0],
                      [8.3, 8.295],
                      [11.751, 0.013],
                      [8.294, -8.303],
                      [0.013, -11.751],
                      [-8.303, -8.294],
                      [-11.751, -0.013],
                      [-8.294, 8.303],
                      [-0.013, 11.751]
                    ],
                    "o": [
                      [-0.013, -11.731],
                      [-8.281, -8.315],
                      [-11.736, -0.006],
                      [-8.3, 8.318],
                      [-0.006, 11.736],
                      [8.318, 8.3],
                      [11.736, 0.006],
                      [8.3, -8.318],
                      [0, 0]
                    ],
                    "v": [
                      [280.5, 119.0],
                      [268.031, 88.961],
                      [237.983, 76.469],
                      [207.938, 88.914],
                      [195.469, 119.017],
                      [207.914, 149.062],
                      [238.017, 161.531],
                      [268.062, 149.086],
                      [280.531, 118.983]
                    ],
                    "c": true
                  }
                ],
                "e": [
                  {
                    "i": [
                      [0, 0],
                      [8.456, 8.447],
                      [11.963, 0.023],
                      [8.45, -8.457],
                      [0.026, -11.965],
                      [-8.454, -8.451],
                      [-11.946, 0.01],
                      [-8.468, 8.414],
                      [0.01, 11.946]
                    ],
                    "o": [
                      [-0.009, -11.962],
                      [-8.434, -8.457],
                      [-11.949, -0.007],
                      [-8.454, 8.433],
                      [-0.004, 11.948],
                      [8.436, 8.453],
                      [11.91, 0.017],
                      [8.453, -8.436],
                      [0, 0]
                    ],
                    "v": [
                      [281.333, 119.0],
                      [268.636, 88.386],
                      [238.04, 75.666],
                      [207.441, 88.341],
                      [194.722, 118.937],
                      [207.396, 149.536],
                      [237.97, 162.2],
                      [268.536, 149.604],
                      [281.2, 119.03]
                    ],
                    "c": true
                  }
                ]
              },
              {
                "i": { "x": 0.5, "y": 0.5 },
                "o": { "x": 0.5, "y": 0.5 },
                "t": 22,
                "s": [
                  {
                    "i": [
                      [0, 0],
                      [8.456, 8.447],
                      [11.963, 0.023],
                      [8.45, -8.457],
                      [0.026, -11.965],
                      [-8.454, -8.451],
                      [-11.946, 0.01],
                      [-8.468, 8.414],
                      [0.01, 11.946]
                    ],
                    "o": [
                      [-0.009, -11.962],
                      [-8.434, -8.457],
                      [-11.949, -0.007],
                      [-8.454, 8.433],
                      [-0.004, 11.948],
                      [8.436, 8.453],
                      [11.91, 0.017],
                      [8.453, -8.436],
                      [0, 0]
                    ],
                    "v": [
                      [281.333, 119.0],
                      [268.636, 88.386],
                      [238.04, 75.666],
                      [207.441, 88.341],
                      [194.722, 118.937],
                      [207.396, 149.536],
                      [237.97, 162.2],
                      [268.536, 149.604],
                      [281.2, 119.03]
                    ],
                    "c": true
                  }
                ],
                "e": [
                  {
                    "i": [
                      [0, 0],
                      [8.627, 8.636],
                      [12.192, -0.025],
                      [8.633, -8.626],
                      [-0.028, -12.191],
                      [-8.629, -8.632],
                      [-12.209, -0.008],
                      [-8.633, 8.633],
                      [-0.007, 12.213]
                    ],
                    "o": [
                      [-0.004, -12.194],
                      [-8.645, -8.625],
                      [-12.21, 0.007],
                      [-8.628, 8.646],
                      [0.004, 12.211],
                      [8.643, 8.63],
                      [12.209, -0.0],
                      [8.668, -8.656],
                      [0, 0]
                    ],
                    "v": [
                      [282.167, 119.0],
                      [269.219, 87.754],
                      [237.963, 74.854],
                      [206.699, 87.804],
                      [193.798, 119.06],
                      [206.748, 150.324],
                      [238.027, 163.28],
                      [269.291, 150.33],
                      [282.303, 119.028]
                    ],
                    "c": true
                  }
                ]
              },
              {
                "i": { "x": 0.5, "y": 0.5 },
                "o": { "x": 0.5, "y": 0.5 },
                "t": 23,
                "s": [
                  {
                    "i": [
                      [0, 0],
                      [8.627, 8.636],
                      [12.192, -0.025],
                      [8.633, -8.626],
                      [-0.028, -12.191],
                      [-8.629, -8.632],
                      [-12.209, -0.008],
                      [-8.633, 8.633],
                      [-0.007, 12.213]
                    ],
                    "o": [
                      [-0.004, -12.194],
                      [-8.645, -8.625],
                      [-12.21, 0.007],
                      [-8.628, 8.646],
                      [0.004, 12.211],
                      [8.643, 8.63],
                      [12.209, -0.0],
                      [8.668, -8.656],
                      [0, 0]
                    ],
                    "v": [
                      [282.167, 119.0],
                      [269.219, 87.754],
                      [237.963, 74.854],
                      [206.699, 87.804],
                      [193.798, 119.06],
                      [206.748, 150.324],
                      [238.027, 163.28],
                      [269.291, 150.33],
                      [282.303, 119.028]
                    ],
                    "c": true
                  }
                ],
                "e": [
                  {
                    "i": [
                      [0, 0],
                      [8.783, 8.788],
                      [12.405, -0.015],
                      [8.789, -8.78],
                      [-0.014, -12.402],
                      [-8.779, -8.786],
                      [-12.401, 0.017],
                      [-8.785, 8.782],
                      [0.033, 12.441]
                    ],
                    "o": [
                      [-0.0, -12.426],
                      [-8.798, -8.767],
                      [-12.423, 0.006],
                      [-8.766, 8.801],
                      [0.007, 12.426],
                      [8.802, 8.769],
                      [12.428, -0.004],
                      [8.77, -8.799],
                      [0, 0]
                    ],
                    "v": [
                      [283.0, 119.0],
                      [269.825, 87.179],
                      [238.02, 74.051],
                      [206.202, 87.23],
                      [193.074, 119.035],
                      [206.253, 150.854],
                      [238.058, 163.982],
                      [269.877, 150.802],
                      [282.982, 118.942]
                    ],
                    "c": true
                  }
                ]
              },
              {
                "i": { "x": 0.5, "y": 0.5 },
                "o": { "x": 0.5, "y": 0.5 },
                "t": 24,
                "s": [
                  {
                    "i": [
                      [0, 0],
                      [8.783, 8.788],
                      [12.405, -0.015],
                      [8.789, -8.78],
                      [-0.014, -12.402],
                      [-8.779, -8.786],
                      [-12.401, 0.017],
                      [-8.785, 8.782],
                      [0.033, 12.441]
                    ],
                    "o": [
                      [-0.0, -12.426],
                      [-8.798, -8.767],
                      [-12.423, 0.006],
                      [-8.766, 8.801],
                      [0.007, 12.426],
                      [8.802, 8.769],
                      [12.428, -0.004],
                      [8.77, -8.799],
                      [0, 0]
                    ],
                    "v": [
                      [283.0, 119.0],
                      [269.825, 87.179],
                      [238.02, 74.051],
                      [206.202, 87.23],
                      [193.074, 119.035],
                      [206.253, 150.854],
                      [238.058, 163.982],
                      [269.877, 150.802],
                      [282.982, 118.942]
                    ],
                    "c": true
                  }
                ],
                "e": [
                  {
                    "i": [
                      [0, 0],
                      [8.939, 8.94],
                      [12.672, 0.012],
                      [8.943, -8.941],
                      [0.03, -12.636],
                      [-8.92, -8.998],
                      [-12.676, -0.014],
                      [-8.998, 8.92],
                      [-0.014, 12.676]
                    ],
                    "o": [
                      [0.004, -12.658],
                      [-8.928, -8.966],
                      [-12.639, -0.001],
                      [-8.963, 8.926],
                      [-0.039, 12.652],
                      [8.923, 8.964],
                      [12.652, 0.039],
                      [8.964, -8.923],
                      [0, 0]
                    ],
                    "v": [
                      [283.833, 119.0],
                      [270.431, 86.603],
                      [238.031, 73.137],
                      [205.659, 86.546],
                      [192.169, 118.89],
                      [205.491, 151.364],
                      [237.89, 164.831],
                      [270.364, 151.509],
                      [283.831, 119.11]
                    ],
                    "c": true
                  }
                ]
              },
              {
                "i": { "x": 0.5, "y": 0.5 },
                "o": { "x": 0.5, "y": 0.5 },
                "t": 25,
                "s": [
                  {
                    "i": [
                      [0, 0],
                      [8.939, 8.94],
                      [12.672, 0.012],
                      [8.943, -8.941],
                      [0.03, -12.636],
                      [-8.92, -8.998],
                      [-12.676, -0.014],
                      [-8.998, 8.92],
                      [-0.014, 12.676]
                    ],
                    "o": [
                      [0.004, -12.658],
                      [-8.928, -8.966],
                      [-12.639, -0.001],
                      [-8.963, 8.926],
                      [-0.039, 12.652],
                      [8.923, 8.964],
                      [12.652, 0.039],
                      [8.964, -8.923],
                      [0, 0]
                    ],
                    "v": [
                      [283.833, 119.0],
                      [270.431, 86.603],
                      [238.031, 73.137],
                      [205.659, 86.546],
                      [192.169, 118.89],
                      [205.491, 151.364],
                      [237.89, 164.831],
                      [270.364, 151.509],
                      [283.831, 119.11]
                    ],
                    "c": true
                  }
                ],
                "e": [
                  {
                    "i": [
                      [0, 0],
                      [9.111, 9.128],
                      [12.881, 0.02],
                      [9.128, -9.111],
                      [0.02, -12.881],
                      [-9.111, -9.128],
                      [-12.881, -0.02],
                      [-9.128, 9.111],
                      [-0.02, 12.881]
                    ],
                    "o": [
                      [0.009, -12.89],
                      [-9.122, -9.094],
                      [-12.897, 0.012],
                      [-9.094, 9.122],
                      [0.012, 12.897],
                      [9.122, 9.094],
                      [12.897, -0.012],
                      [9.094, -9.122],
                      [0, 0]
                    ],
                    "v": [
                      [284.667, 119.0],
                      [271.014, 85.972],
                      [238.01, 72.301],
                      [204.972, 85.986],
                      [191.301, 118.99],
                      [204.986, 152.028],
                      [237.99, 165.699],
                      [271.028, 152.014],
                      [284.699, 119.01]
                    ],
                    "c": true
                  }
                ]
              },
              {
                "i": { "x": 0.5, "y": 0.5 },
                "o": { "x": 0.5, "y": 0.5 },
                "t": 26,
                "s": [
                  {
                    "i": [
                      [0, 0],
                      [9.111, 9.128],
                      [12.881, 0.02],
                      [9.128, -9.111],
                      [0.02, -12.881],
                      [-9.111, -9.128],
                      [-12.881, -0.02],
                      [-9.128, 9.111],
                      [-0.02, 12.881]
                    ],
                    "o": [
                      [0.009, -12.89],
                      [-9.122, -9.094],
                      [-12.897, 0.012],
                      [-9.094, 9.122],
                      [0.012, 12.897],
                      [9.122, 9.094],
                      [12.897, -0.012],
                      [9.094, -9.122],
                      [0, 0]
                    ],
                    "v": [
                      [284.667, 119.0],
                      [271.014, 85.972],
                      [238.01, 72.301],
                      [204.972, 85.986],
                      [191.301, 118.99],
                      [204.986, 152.028],
                      [237.99, 165.699],
                      [271.028, 152.014],
                      [284.699, 119.01]
                    ],
                    "c": true
                  }
                ],
                "e": [
                  {
                    "i": [
                      [0, 0],
                      [9.267, 9.28],
                      [13.129, 0.011],
                      [9.28, -9.267],
                      [0.011, -13.129],
                      [-9.267, -9.28],
                      [-13.129, -0.011],
                      [-9.28, 9.267],
                      [-0.011, 13.129]
                    ],
                    "o": [
                      [0.013, -13.122],
                      [-9.291, -9.276],
                      [-13.115, 0.009],
                      [-9.276, 9.291],
                      [0.009, 13.115],
                      [9.291, 9.276],
                      [13.115, -0.009],
                      [9.276, -9.291],
                      [0, 0]
                    ],
                    "v": [
                      [285.5, 119.0],
                      [271.62, 85.396],
                      [237.989, 71.466],
                      [204.396, 85.38],
                      [190.466, 119.011],
                      [204.38, 152.604],
                      [238.011, 166.534],
                      [271.604, 152.62],
                      [285.534, 118.989]
                    ],
                    "c": true
                  }
                ]
              },
              {
                "i": { "x": 0.5, "y": 0.5 },
                "o": { "x": 0.5, "y": 0.5 },
                "t": 27,
                "s": [
                  {
                    "i": [
                      [0, 0],
                      [9.267, 9.28],
                      [13.129, 0.011],
                      [9.28, -9.267],
                      [0.011, -13.129],
                      [-9.267, -9.28],
                      [-13.129, -0.011],
                      [-9.28, 9.267],
                      [-0.011, 13.129]
                    ],
                    "o": [
                      [0.013, -13.122],
                      [-9.291, -9.276],
                      [-13.115, 0.009],
                      [-9.276, 9.291],
                      [0.009, 13.115],
                      [9.291, 9.276],
                      [13.115, -0.009],
                      [9.276, -9.291],
                      [0, 0]
                    ],
                    "v": [
                      [285.5, 119.0],
                      [271.62, 85.396],
                      [237.989, 71.466],
                      [204.396, 85.38],
                      [190.466, 119.011],
                      [204.38, 152.604],
                      [238.011, 166.534],
                      [271.604, 152.62],
                      [285.534, 118.989]
                    ],
                    "c": true
                  }
                ],
                "e": [
                  {
                    "i": [
                      [0, 0],
                      [9.423, 9.432],
                      [13.378, 0.002],
                      [9.414, -9.459],
                      [-0.018, -13.322],
                      [-9.42, -9.433],
                      [-13.324, 0.015],
                      [-9.434, 9.417],
                      [0.015, 13.324]
                    ],
                    "o": [
                      [0.018, -13.354],
                      [-9.461, -9.458],
                      [-13.372, 0.023],
                      [-9.42, 9.449],
                      [0.009, 13.331],
                      [9.447, 9.417],
                      [13.33, -0.012],
                      [9.432, -9.411],
                      [0, 0]
                    ],
                    "v": [
                      [286.333, 119.0],
                      [272.225, 84.821],
                      [237.967, 70.631],
                      [203.788, 84.853],
                      [189.686, 119.01],
                      [203.83, 153.156],
                      [237.987, 167.259],
                      [272.133, 153.115],
                      [286.259, 119.013]
                    ],
                    "c": true
                  }
                ]
              },
              {
                "i": { "x": 0.5, "y": 0.5 },
                "o": { "x": 0.5, "y": 0.5 },
                "t": 28,
                "s": [
                  {
                    "i": [
                      [0, 0],
                      [9.423, 9.432],
                      [13.378, 0.002],
                      [9.414, -9.459],
                      [-0.018, -13.322],
                      [-9.42, -9.433],
                      [-13.324, 0.015],
                      [-9.434, 9.417],
                      [0.015, 13.324]
                    ],
                    "o": [
                      [0.018, -13.354],
                      [-9.461, -9.458],
                      [-13.372, 0.023],
                      [-9.42, 9.449],
                      [0.009, 13.331],
                      [9.447, 9.417],
                      [13.33, -0.012],
                      [9.432, -9.411],
                      [0, 0]
                    ],
                    "v": [
                      [286.333, 119.0],
                      [272.225, 84.821],
                      [237.967, 70.631],
                      [203.788, 84.853],
                      [189.686, 119.01],
                      [203.83, 153.156],
                      [237.987, 167.259],
                      [272.133, 153.115],
                      [286.259, 119.013]
                    ],
                    "c": true
                  }
                ],
                "e": [
                  {
                    "i": [
                      [0, 0],
                      [9.576, 9.585],
                      [13.591, 0.012],
                      [9.621, -9.594],
                      [0.009, -13.589],
                      [-9.594, -9.621],
                      [-13.589, -0.009],
                      [-9.621, 9.594],
                      [-0.009, 13.589]
                    ],
                    "o": [
                      [-0.018, -13.57],
                      [-9.577, -9.615],
                      [-13.602, -0.018],
                      [-9.603, 9.615],
                      [0.019, 13.587],
                      [9.615, 9.603],
                      [13.587, -0.019],
                      [9.603, -9.615],
                      [0, 0]
                    ],
                    "v": [
                      [287.167, 119.0],
                      [272.776, 84.268],
                      [238.024, 69.828],
                      [203.19, 84.192],
                      [188.772, 118.999],
                      [203.192, 153.81],
                      [237.999, 168.228],
                      [272.81, 153.808],
                      [287.228, 119.001]
                    ],
                    "c": true
                  }
                ]
              },
              {
                "i": { "x": 0.5, "y": 0.5 },
                "o": { "x": 0.5, "y": 0.5 },
                "t": 29,
                "s": [
                  {
                    "i": [
                      [0, 0],
                      [9.576, 9.585],
                      [13.591, 0.012],
                      [9.621, -9.594],
                      [0.009, -13.589],
                      [-9.594, -9.621],
                      [-13.589, -0.009],
                      [-9.621, 9.594],
                      [-0.009, 13.589]
                    ],
                    "o": [
                      [-0.018, -13.57],
                      [-9.577, -9.615],
                      [-13.602, -0.018],
                      [-9.603, 9.615],
                      [0.019, 13.587],
                      [9.615, 9.603],
                      [13.587, -0.019],
                      [9.603, -9.615],
                      [0, 0]
                    ],
                    "v": [
                      [287.167, 119.0],
                      [272.776, 84.268],
                      [238.024, 69.828],
                      [203.19, 84.192],
                      [188.772, 118.999],
                      [203.192, 153.81],
                      [237.999, 168.228],
                      [272.81, 153.808],
                      [287.228, 119.001]
                    ],
                    "c": true
                  }
                ],
                "e": [
                  {
                    "i": [
                      [0, 0],
                      [9.748, 9.774],
                      [13.799, 0.02],
                      [9.774, -9.748],
                      [0.02, -13.799],
                      [-9.748, -9.774],
                      [-13.799, -0.02],
                      [-9.774, 9.748],
                      [-0.02, 13.799]
                    ],
                    "o": [
                      [-0.013, -13.802],
                      [-9.771, -9.744],
                      [-13.804, 0.019],
                      [-9.744, 9.771],
                      [0.019, 13.804],
                      [9.771, 9.744],
                      [13.804, -0.019],
                      [9.744, -9.771],
                      [0, 0]
                    ],
                    "v": [
                      [288.0, 119.0],
                      [273.359, 83.637],
                      [238.003, 68.992],
                      [202.637, 83.641],
                      [187.992, 118.997],
                      [202.641, 154.363],
                      [237.997, 169.008],
                      [273.363, 154.359],
                      [288.008, 119.003]
                    ],
                    "c": true
                  }
                ]
              },
              {
                "i": { "x": 0.5, "y": 0.5 },
                "o": { "x": 0.5, "y": 0.5 },
                "t": 30,
                "s": [
                  {
                    "i": [
                      [0, 0],
                      [9.748, 9.774],
                      [13.799, 0.02],
                      [9.774, -9.748],
                      [0.02, -13.799],
                      [-9.748, -9.774],
                      [-13.799, -0.02],
                      [-9.774, 9.748],
                      [-0.02, 13.799]
                    ],
                    "o": [
                      [-0.013, -13.802],
                      [-9.771, -9.744],
                      [-13.804, 0.019],
                      [-9.744, 9.771],
                      [0.019, 13.804],
                      [9.771, 9.744],
                      [13.804, -0.019],
                      [9.744, -9.771],
                      [0, 0]
                    ],
                    "v": [
                      [288.0, 119.0],
                      [273.359, 83.637],
                      [238.003, 68.992],
                      [202.637, 83.641],
                      [187.992, 118.997],
                      [202.641, 154.363],
                      [237.997, 169.008],
                      [273.363, 154.359],
                      [288.008, 119.003]
                    ],
                    "c": true
                  }
                ],
                "e": [
                  {
                    "i": [
                      [0, 0],
                      [9.748, 9.774],
                      [13.799, 0.02],
                      [9.774, -9.748],
                      [0.02, -13.799],
                      [-9.748, -9.774],
                      [-13.799, -0.02],
                      [-9.774, 9.748],
                      [-0.02, 13.799]
                    ],
                    "o": [
                      [-0.013, -13.802],
                      [-9.771, -9.744],
                      [-13.804, 0.019],
                      [-9.744, 9.771],
                      [0.019, 13.804],
                      [9.771, 9.744],
                      [13.804, -0.019],
                      [9.744, -9.771],
                      [0, 0]
                    ],
                    "v": [
                      [288.0, 119.0],
                      [273.359, 83.637],
                      [238.003, 68.992],
                      [202.637, 83.641],
                      [187.992, 118.997],
                      [202.641, 154.363],
                      [237.997, 169.008],
                      [273.363, 154.359],
                      [288.008, 119.003]
                    ],
                    "c": true
                  }
                ]
              },
              { "t": 31 }
            ]
          },
          "o": { "k": 100, "ix": 1, "a": 0 },
          "x": { "k": 0, "ix": 2, "a": 0 },
          "nm": "Mask 1"
        }
      ]
    }
  ]
}
